{
    "fecha_inicio": "1734199657",
    "exchange": "BYBIT",
    "activo": "ETH",
    "inverso": true,
    "balance_inicial": "0.00120874",
    "balance_actual": "4.719612122",
    "ganancias_del_grid": "0.0",
    "ganancia_actual": "1.093278792418424",
    "riesgo_maximo": "-2.08634995784804",
    "cantidad_parejeas_long": "10",
    "parejas_completadas": "4",
    "parejas": [
        {
            "general": {
                "fecha": "2024-12-14 - 05:26:45 PM",
                "beneficios": "0"
            },
            "compra": {
                "orderId": "5339a40f-1b2e-4842-b07b-7a0fd0329338",
                "price": 3847.95,
                "cantidad": "0.00129939318338336",
                "monto": "5.0",
                "ejecutada": false,
                "fecha_ejecucion": "-"
            },
            "venta": {
                "orderId": "",
                "price": "3859.15",
                "cantidad": "0.00129939318338336",
                "monto": "5.014553203653894",
                "ejecutada": false,
                "fecha_ejecucion": "-"
            },
            "sl": {
                "orderId": ""
            }
        },
        {
            "general": {
                "fecha": "2024-12-14 - 04:12:47 PM",
                "beneficios": "0"
            },
            "compra": {
                "orderId": "38452393-d4d0-466b-8964-c4f81e8875b7",
                "price": 3836.85,
                "cantidad": "0.0013031523254753248",
                "monto": "5.0",
                "ejecutada": false,
                "fecha_ejecucion": "-"
            },
            "venta": {
                "orderId": "",
                "price": "3847.99",
                "cantidad": "0.0013031523254753248",
                "monto": "5.014517116905795",
                "ejecutada": false,
                "fecha_ejecucion": "-"
            },
            "sl": {
                "orderId": ""
            }
        },
        {
            "general": {
                "fecha": "2024-12-14 - 04:02:05 PM",
                "beneficios": "0"
            },
            "compra": {
                "orderId": "2350533c-4907-44e5-8e0f-965f13d48f52",
                "price": 3825.75,
                "cantidad": "0.0013069332810560022",
                "monto": "5.0",
                "ejecutada": false,
                "fecha_ejecucion": "-"
            },
            "venta": {
                "orderId": "",
                "price": "3836.86",
                "cantidad": "0.0013069332810560022",
                "monto": "5.014520028752533",
                "ejecutada": false,
                "fecha_ejecucion": "-"
            },
            "sl": {
                "orderId": ""
            }
        },
        {
            "general": {
                "fecha": "2024-12-14 - 03:53:02 PM",
                "beneficios": "0"
            },
            "compra": {
                "orderId": "0c708886-d3de-4d85-a739-c8b2dc31384b",
                "price": 3814.7,
                "cantidad": "0.0013107190604765774",
                "monto": "5.0",
                "ejecutada": false,
                "fecha_ejecucion": "-"
            },
            "venta": {
                "orderId": "",
                "price": "3825.77",
                "cantidad": "0.0013107190604765774",
                "monto": "5.014509659999476",
                "ejecutada": false,
                "fecha_ejecucion": "-"
            },
            "sl": {
                "orderId": ""
            }
        },
        {
            "general": {
                "fecha": "2024-12-14 - 02:30:59 PM",
                "beneficios": "0.0"
            },
            "compra": {
                "orderId": "81ecf5f4-95bf-49fd-a589-eb2386f9ea91",
                "price": "3847.95942711",
                "cantidad": "0.0012993900000019588",
                "monto": "5.0",
                "ejecutada": true,
                "fecha_ejecucion": "2024-12-14 - 03:20:16 PM"
            },
            "venta": {
                "orderId": "f429d023-d3ea-4703-8f8b-0f9cf807d5d7",
                "price": "3859.42432826",
                "cantidad": 0.0012955300000024154,
                "monto": "5.0",
                "ejecutada": true,
                "fecha_ejecucion": "2024-12-14 - 05:26:36 PM"
            },
            "sl": {
                "orderId": ""
            }
        },
        {
            "general": {
                "fecha": "2024-12-14 - 01:32:32 PM",
                "beneficios": "0.0"
            },
            "compra": {
                "orderId": "4213aaaf-29cf-45ac-9a21-6ef1aae49181",
                "price": "3825.75960456",
                "cantidad": "0.001306930000003241",
                "monto": "5.0",
                "ejecutada": true,
                "fecha_ejecucion": "2024-12-14 - 03:52:53 PM"
            },
            "venta": {
                "orderId": "0c61571c-ee0e-4cd8-960d-ba34cd89a99a",
                "price": "3837.2101947",
                "cantidad": 0.0013030300000000153,
                "monto": "5.0",
                "ejecutada": true,
                "fecha_ejecucion": "2024-12-14 - 04:01:12 PM"
            },
            "sl": {
                "orderId": ""
            }
        },
        {
            "general": {
                "fecha": "2024-12-14 - 01:13:16 PM",
                "beneficios": "0.0"
            },
            "compra": {
                "orderId": "f6e052a3-6879-447a-8f5d-2cc59a2dddf2",
                "price": "3836.85684687",
                "cantidad": "0.0013031500000003544",
                "monto": "5.0",
                "ejecutada": true,
                "fecha_ejecucion": "2024-12-14 - 01:32:19 PM"
            },
            "venta": {
                "orderId": "62ce5513-a95f-49a8-9d5d-788894349bda",
                "price": "3848.01865519",
                "cantidad": 0.0012993700000014994,
                "monto": "5.0",
                "ejecutada": true,
                "fecha_ejecucion": "2024-12-14 - 02:26:49 PM"
            },
            "sl": {
                "orderId": ""
            }
        },
        {
            "general": {
                "fecha": "2024-12-14 - 01:08:50 PM",
                "beneficios": "0"
            },
            "compra": {
                "orderId": "63d66c1b-6ecf-47cb-9f15-06398e70f45a",
                "price": 3870.3,
                "cantidad": 0.001291889517608454,
                "monto": "5.0",
                "ejecutada": false,
                "fecha_ejecucion": "-"
            },
            "venta": {
                "orderId": "",
                "price": "3881.5639859999997",
                "cantidad": 0.001291889517608454,
                "monto": "5.014551825439888",
                "ejecutada": false,
                "fecha_ejecucion": "-"
            },
            "sl": {
                "orderId": ""
            }
        },
        {
            "general": {
                "fecha": "2024-12-14 - 01:08:23 PM",
                "beneficios": "0"
            },
            "compra": {
                "orderId": "7ca05186-e586-4fdf-afe7-cb9d73080a9a",
                "price": "3859.42432826",
                "cantidad": "0.0012955300000024154",
                "monto": "5.0",
                "ejecutada": true,
                "fecha_ejecucion": "2024-12-14 - 01:08:25 PM"
            },
            "venta": {
                "orderId": "de60b304-bb3a-4091-8845-c6d49164a045",
                "price": "3870.3415349999996",
                "cantidad": 0.0012956220929479288,
                "monto": "5.0145",
                "ejecutada": false,
                "fecha_ejecucion": "-"
            },
            "sl": {
                "orderId": ""
            }
        },
        {
            "general": {
                "fecha": "2024-12-14 - 01:08:14 PM",
                "beneficios": "0.0"
            },
            "compra": {
                "orderId": "0792b811-ae12-47d5-96ba-d8aeec93b3eb",
                "price": "3847.95942711",
                "cantidad": "0.0012993900000019588",
                "monto": "5.0",
                "ejecutada": true,
                "fecha_ejecucion": "2024-12-14 - 01:13:07 PM"
            },
            "venta": {
                "orderId": "b54bd8ba-cb5b-413b-8cf0-bb1a0496b145",
                "price": "3859.15623408",
                "cantidad": 0.001295620000000329,
                "monto": "5.0",
                "ejecutada": true,
                "fecha_ejecucion": "2024-12-14 - 02:30:45 PM"
            },
            "sl": {
                "orderId": ""
            }
        }
    ]
}